{
  "name": "WhatsApp to Telegram Notifications",
  "nodes": [
    {
      "parameters": {},
      "id": "c0b2e2b0-5c3a-4b8e-9c2e-8f5d3a1b2c4d",
      "name": "Start",
      "type": "n8n-nodes-base.start",
      "typeVersion": 1,
      "position": [
        250,
        300
      ]
    },
    {
      "parameters": {
        "httpMethod": "POST",
        "path": "whatsapp-notification",
        "responseMode": "responseNode",
        "options": {}
      },
      "id": "d1c3f3c1-6d4b-5c9f-0d3f-9g6e4b2c3d5e",
      "name": "Webhook - WhatsApp Message",
      "type": "n8n-nodes-base.webhook",
      "typeVersion": 1,
      "position": [
        450,
        300
      ],
      "webhookId": "whatsapp-notification"
    },
    {
      "parameters": {
        "chatId": "={{ $json.body.telegram_chat_id }}",
        "text": "📱 *Nouveau message WhatsApp*\n\n*De:* {{ $json.body.sender_name }}\n*Numéro:* {{ $json.body.sender_phone }}\n\n*Message:*\n{{ $json.body.message }}\n\n_{{ $json.body.timestamp }}_",
        "parse_mode": "Markdown",
        "disable_web_page_preview": true
      },
      "id": "e2d4g4d2-7e5c-6d0g-1e4g-0h7f5c3d4e6f",
      "name": "Send Telegram Notification",
      "type": "n8n-nodes-base.telegram",
      "typeVersion": 1,
      "position": [
        700,
        300
      ],
      "credentials": {
        "telegramApi": {
          "id": "YOUR_TELEGRAM_CREDENTIAL_ID",
          "name": "Telegram Bot Credential"
        }
      }
    },
    {
      "parameters": {
        "statusCode": 200,
        "responseData": "{\"status\":\"ok\",\"message\":\"Notification envoyée sur Telegram\"}",
        "options": {}
      },
      "id": "f3e5h5e3-8f6d-7e1h-2f5h-1i8g6d4e5f7g",
      "name": "Response to Webhook",
      "type": "n8n-nodes-base.respondToWebhook",
      "typeVersion": 1,
      "position": [
        700,
        500
      ]
    },
    {
      "parameters": {
        "conditions": {
          "options": {
            "caseSensitive": true,
            "leftValue": "",
            "typeValidation": "strict"
          },
          "conditions": [
            {
              "id": "condition-1",
              "leftValue": "={{ $json.body.message }}",
              "rightValue": "urgent",
              "operator": {
                "type": "string",
                "operation": "contains"
              }
            }
          ],
          "combinator": "and"
        }
      },
      "id": "g4f6i6f4-9g7e-8f2i-3g6i-2j9h7e5f6g8h",
      "name": "Check if Urgent",
      "type": "n8n-nodes-base.if",
      "typeVersion": 1,
      "position": [
        950,
        300
      ]
    },
    {
      "parameters": {
        "chatId": "={{ $json.body.telegram_chat_id }}",
        "text": "🚨 *MESSAGE URGENT WhatsApp* 🚨\n\n*De:* {{ $json.body.sender_name }}\n*Numéro:* {{ $json.body.sender_phone }}\n\n*Message:*\n{{ $json.body.message }}\n\n_{{ $json.body.timestamp }}_",
        "parse_mode": "Markdown",
        "disable_web_page_preview": true
      },
      "id": "h5g7j7g5-0h8f-9g3j-4h7j-3k0i8f6g7h9i",
      "name": "Send Urgent Notification",
      "type": "n8n-nodes-base.telegram",
      "typeVersion": 1,
      "position": [
        1200,
        200
      ],
      "credentials": {
        "telegramApi": {
          "id": "YOUR_TELEGRAM_CREDENTIAL_ID",
          "name": "Telegram Bot Credential"
        }
      }
    }
  ],
  "pinData": {},
  "settings": {
    "executionOrder": "v1"
  },
  "staticData": {
    "node:d1c3f3c1-6d4b-5c9f-0d3f-9g6e4b2c3d5e": {
      "webhookId": "whatsapp-notification"
    }
  },
  "tags": [],
  "connections": {
    "Webhook - WhatsApp Message": {
      "main": [
        [
          {
            "node": "Send Telegram Notification",
            "type": "main",
            "index": 0
          }
        ]
      ]
    },
    "Send Telegram Notification": {
      "main": [
        [
          {
            "node": "Response to Webhook",
            "type": "main",
            "index": 0
          },
          {
            "node": "Check if Urgent",
            "type": "main",
            "index": 0
          }
        ]
      ]
    },
    "Check if Urgent": {
      "main": [
        [
          {
            "node": "Send Urgent Notification",
            "type": "main",
            "index": 0
          }
        ]
      ]
    }
  }
}